brainfucky/__init__.py
brainfucky-0.1.dev1.dist-info/DESCRIPTION.rst
brainfucky-0.1.dev1.dist-info/METADATA
brainfucky-0.1.dev1.dist-info/RECORD
brainfucky-0.1.dev1.dist-info/WHEEL
brainfucky-0.1.dev1.dist-info/entry_points.txt
brainfucky-0.1.dev1.dist-info/metadata.json
brainfucky-0.1.dev1.dist-info/top_level.txt
