Metadata-Version: 2.0
Name: brainfucky
Version: 0.1.dev1
Summary: Brainfuck interpreter in python.
Home-page: https://github.com/meetmangukiya/brainfucky
Author: Meet Mangukiya
Author-email: meetmangukiya98@gmail.com
License: MIT
Platform: UNKNOWN
Classifier: License :: OSI Approved :: MIT License
Classifier: Programming Language :: Python
Classifier: Programming Language :: Python :: 3
Classifier: Programming Language :: Python :: 3.6
Classifier: Programming Language :: Python :: Implementation :: CPython
Classifier: Programming Language :: Python :: Implementation :: PyPy
Requires-Python: >=3
